tribool.py
tribool-0.7.2.dist-info/DESCRIPTION.rst
tribool-0.7.2.dist-info/METADATA
tribool-0.7.2.dist-info/RECORD
tribool-0.7.2.dist-info/WHEEL
tribool-0.7.2.dist-info/metadata.json
tribool-0.7.2.dist-info/top_level.txt
